lalita/__init__.py
lalita/ircbot.py
lalita/core/__init__.py
lalita/core/dispatcher.py
lalita/core/events.py
lalita/core/flowcontrol.py
lalita/core/tests/__init__.py
lalita/core/tests/test_dispatcher.py
lalita/core/tests/test_events.py
lalita/core/tests/test_flowcontrol.py
lalita/core/tests/test_ircbot.py
lalita/core/tests/test_metacommands.py
lalita/core/tests/plugins/__init__.py
lalita/core/tests/plugins/deathmatch.py
lalita/plugins/__init__.py
lalita/plugins/archives_search.py
lalita/plugins/example.py
lalita/plugins/freenode.py
lalita/plugins/fumador.py
lalita/plugins/misc.py
lalita/plugins/moin_search.py
lalita/plugins/photo.py
lalita/plugins/randomer.py
lalita/plugins/seen.py
lalita/plugins/url.py
lalita/plugins/randomer_utils/__init__.py
lalita/plugins/randomer_utils/randomer.py
lalita/plugins/tests/__init__.py
lalita/plugins/tests/helper.py
lalita/plugins/tests/test_example.py
lalita/plugins/tests/test_fumador.py
lalita/plugins/tests/test_misc.py
lalita/plugins/tests/test_photo.py
lalita/plugins/tests/test_seen.py
lalita-0.1.3.data/scripts/ircbot.py
lalita-0.1.3.dist-info/DESCRIPTION.rst
lalita-0.1.3.dist-info/METADATA
lalita-0.1.3.dist-info/RECORD
lalita-0.1.3.dist-info/WHEEL
lalita-0.1.3.dist-info/metadata.json
lalita-0.1.3.dist-info/top_level.txt
